{"data":[{"name":"decreasing","entryType":"measure","startTime":38042.45469999313,"duration":2.2533000111579895,"detail":null},{"name":"decreasing","entryType":"measure","startTime":38086.20529997349,"duration":5.5135000348091125,"detail":null},{"name":"decreasing","entryType":"measure","startTime":38289.69359999895,"duration":5.79229998588562,"detail":null},{"name":"decreasing","entryType":"measure","startTime":38387.28499996662,"duration":1.1097000241279602,"detail":null},{"name":"decreasing","entryType":"measure","startTime":38540.749099969864,"duration":2.1938000321388245,"detail":null},{"name":"decreasing","entryType":"measure","startTime":38645.04469996691,"duration":1.2232000231742859,"detail":null},{"name":"decreasing","entryType":"measure","startTime":39092.746899962425,"duration":75.66140002012253,"detail":null},{"name":"decreasing","entryType":"measure","startTime":39415.504799962044,"duration":1.1180000305175781,"detail":null},{"name":"decreasing","entryType":"measure","startTime":39579.58340001106,"duration":3.89029997587204,"detail":null},{"name":"decreasing","entryType":"measure","startTime":39786.71779996157,"duration":1.5301000475883484,"detail":null},{"name":"decreasing","entryType":"measure","startTime":40987.28979998827,"duration":6.066699981689453,"detail":null},{"name":"decreasing","entryType":"measure","startTime":41073.55579996109,"duration":5.0432000160217285,"detail":null},{"name":"decreasing","entryType":"measure","startTime":41309.65929996967,"duration":3.9330000281333923,"detail":null},{"name":"decreasing","entryType":"measure","startTime":41379.11449998617,"duration":2.4478999972343445,"detail":null},{"name":"decreasing","entryType":"measure","startTime":41470.533599972725,"duration":4.922399997711182,"detail":null},{"name":"decreasing","entryType":"measure","startTime":41570.4700999856,"duration":4.951099991798401,"detail":null},{"name":"decreasing","entryType":"measure","startTime":41653.077899992466,"duration":2.1086000204086304,"detail":null},{"name":"decreasing","entryType":"measure","startTime":41750.39739996195,"duration":1.5081000328063965,"detail":null},{"name":"decreasing","entryType":"measure","startTime":41865.38839995861,"duration":2.0812000036239624,"detail":null},{"name":"decreasing","entryType":"measure","startTime":41999.12619996071,"duration":3.909700036048889,"detail":null},{"name":"decreasing","entryType":"measure","startTime":42173.583599984646,"duration":5.427699983119965,"detail":null},{"name":"decreasing","entryType":"measure","startTime":42188.50720000267,"duration":6.759700000286102,"detail":null},{"name":"decreasing","entryType":"measure","startTime":42228.09020000696,"duration":30.97519999742508,"detail":null},{"name":"decreasing","entryType":"measure","startTime":42354.388499975204,"duration":2.2085999846458435,"detail":null},{"name":"decreasing","entryType":"measure","startTime":42400.04899996519,"duration":2.449400007724762,"detail":null},{"name":"decreasing","entryType":"measure","startTime":42780.85969996452,"duration":1.1620000004768372,"detail":null},{"name":"decreasing","entryType":"measure","startTime":42863.72469997406,"duration":3.499400019645691,"detail":null},{"name":"decreasing","entryType":"measure","startTime":42969.11500000954,"duration":2.202899992465973,"detail":null},{"name":"decreasing","entryType":"measure","startTime":43039.7120000124,"duration":3.9280999898910522,"detail":null},{"name":"decreasing","entryType":"measure","startTime":43071.67879998684,"duration":1.6798999905586243,"detail":null},{"name":"decreasing","entryType":"measure","startTime":43516.09789997339,"duration":3.6424999833106995,"detail":null},{"name":"decreasing","entryType":"measure","startTime":43805.63029998541,"duration":2.463599979877472,"detail":null},{"name":"decreasing","entryType":"measure","startTime":43883.6263999939,"duration":3.9311999678611755,"detail":null},{"name":"decreasing","entryType":"measure","startTime":43980.62779998779,"duration":1.655900001525879,"detail":null},{"name":"decreasing","entryType":"measure","startTime":44053.14889997244,"duration":4.830300033092499,"detail":null},{"name":"decreasing","entryType":"measure","startTime":44389.861199975014,"duration":2.544000029563904,"detail":null},{"name":"decreasing","entryType":"measure","startTime":44778.1344999671,"duration":5.459200024604797,"detail":null},{"name":"decreasing","entryType":"measure","startTime":44862.67339998484,"duration":1.1664999723434448,"detail":null},{"name":"decreasing","entryType":"measure","startTime":44950.03959995508,"duration":4.0277000069618225,"detail":null},{"name":"decreasing","entryType":"measure","startTime":45037.89739996195,"duration":3.9592000246047974,"detail":null},{"name":"decreasing","entryType":"measure","startTime":45125.57829999924,"duration":2.261399984359741,"detail":null},{"name":"decreasing","entryType":"measure","startTime":45198.819599986076,"duration":3.3865000009536743,"detail":null},{"name":"decreasing","entryType":"measure","startTime":45245.494199991226,"duration":3.758799970149994,"detail":null},{"name":"decreasing","entryType":"measure","startTime":45250.83709996939,"duration":42.278500020504,"detail":null},{"name":"decreasing","entryType":"measure","startTime":45603.712700009346,"duration":4.734699964523315,"detail":null},{"name":"decreasing","entryType":"measure","startTime":45834.26370000839,"duration":2.6174999475479126,"detail":null},{"name":"decreasing","entryType":"measure","startTime":45867.588800013065,"duration":2.8347999453544617,"detail":null},{"name":"decreasing","entryType":"measure","startTime":45944.51159995794,"duration":1.6455000042915344,"detail":null},{"name":"decreasing","entryType":"measure","startTime":45978.764999985695,"duration":2.691699981689453,"detail":null},{"name":"decreasing","entryType":"measure","startTime":46113.287099957466,"duration":1.1193000078201294,"detail":null},{"name":"decreasing","entryType":"measure","startTime":46327.94059997797,"duration":1.7439000010490417,"detail":null},{"name":"decreasing","entryType":"measure","startTime":46395.50439995527,"duration":2.5753000378608704,"detail":null},{"name":"decreasing","entryType":"measure","startTime":46466.90359997749,"duration":2.6891000270843506,"detail":null},{"name":"decreasing","entryType":"measure","startTime":46697.438499987125,"duration":2.1383000016212463,"detail":null},{"name":"decreasing","entryType":"measure","startTime":46848.23679995537,"duration":1.194200038909912,"detail":null},{"name":"decreasing","entryType":"measure","startTime":47153.215799987316,"duration":2.192900002002716,"detail":null},{"name":"decreasing","entryType":"measure","startTime":47258.614199995995,"duration":50.657499969005585,"detail":null},{"name":"decreasing","entryType":"measure","startTime":47396.5992000103,"duration":2.632200002670288,"detail":null},{"name":"decreasing","entryType":"measure","startTime":47455.03979998827,"duration":2.607199966907501,"detail":null},{"name":"decreasing","entryType":"measure","startTime":47933.129799962044,"duration":1.547700047492981,"detail":null},{"name":"decreasing","entryType":"measure","startTime":47957.88440001011,"duration":1.2656999826431274,"detail":null},{"name":"decreasing","entryType":"measure","startTime":48141.321799993515,"duration":1.1951000094413757,"detail":null},{"name":"decreasing","entryType":"measure","startTime":48425.744599998,"duration":7.095200002193451,"detail":null},{"name":"decreasing","entryType":"measure","startTime":48513.994199991226,"duration":2.1328999996185303,"detail":null},{"name":"decreasing","entryType":"measure","startTime":48539.94609999657,"duration":3.063199996948242,"detail":null},{"name":"decreasing","entryType":"measure","startTime":48711.84819996357,"duration":1.6522000432014465,"detail":null},{"name":"decreasing","entryType":"measure","startTime":48835.77609997988,"duration":1.3604999780654907,"detail":null},{"name":"decreasing","entryType":"measure","startTime":49166.052599966526,"duration":1.5854000449180603,"detail":null},{"name":"decreasing","entryType":"measure","startTime":49189.171499967575,"duration":2.8652000427246094,"detail":null},{"name":"decreasing","entryType":"measure","startTime":49265.34419995546,"duration":48.12640005350113,"detail":null},{"name":"decreasing","entryType":"measure","startTime":49374.79369997978,"duration":1.1399999856948853,"detail":null},{"name":"decreasing","entryType":"measure","startTime":49432.114699959755,"duration":6.2909000515937805,"detail":null},{"name":"decreasing","entryType":"measure","startTime":49472.75699996948,"duration":1.2032999992370605,"detail":null},{"name":"decreasing","entryType":"measure","startTime":49660.431299984455,"duration":2.1870999932289124,"detail":null},{"name":"decreasing","entryType":"measure","startTime":49682.142699956894,"duration":1.7273000478744507,"detail":null},{"name":"decreasing","entryType":"measure","startTime":49714.02999997139,"duration":7.446300029754639,"detail":null},{"name":"decreasing","entryType":"measure","startTime":49857.214999973774,"duration":3.992200016975403,"detail":null},{"name":"decreasing","entryType":"measure","startTime":49925.44010001421,"duration":1.1505999565124512,"detail":null},{"name":"decreasing","entryType":"measure","startTime":50205.080199956894,"duration":1.7070000171661377,"detail":null},{"name":"decreasing","entryType":"measure","startTime":50524.553699970245,"duration":3.1359000205993652,"detail":null},{"name":"decreasing","entryType":"measure","startTime":50549.26209998131,"duration":4.513199985027313,"detail":null},{"name":"decreasing","entryType":"measure","startTime":50628.15839999914,"duration":2.1448000073432922,"detail":null},{"name":"decreasing","entryType":"measure","startTime":50716.5651999712,"duration":17.286100029945374,"detail":null},{"name":"decreasing","entryType":"measure","startTime":51033.63569998741,"duration":2.634999990463257,"detail":null},{"name":"decreasing","entryType":"measure","startTime":51273.683999955654,"duration":3.720200002193451,"detail":null},{"name":"decreasing","entryType":"measure","startTime":51273.683999955654,"duration":29.59440004825592,"detail":null},{"name":"decreasing","entryType":"measure","startTime":51568.41679996252,"duration":3.0645000338554382,"detail":null},{"name":"decreasing","entryType":"measure","startTime":51593.936999976635,"duration":2.348800003528595,"detail":null},{"name":"decreasing","entryType":"measure","startTime":51624.27459996939,"duration":1.150700032711029,"detail":null},{"name":"decreasing","entryType":"measure","startTime":51803.90539997816,"duration":2.592400014400482,"detail":null},{"name":"decreasing","entryType":"measure","startTime":52200.580099999905,"duration":2.216499984264374,"detail":null},{"name":"decreasing","entryType":"measure","startTime":52683.4171000123,"duration":3.3817999958992004,"detail":null},{"name":"decreasing","entryType":"measure","startTime":52728.10679996014,"duration":17.425200045108795,"detail":null},{"name":"decreasing","entryType":"measure","startTime":52728.10679996014,"duration":18.90690004825592,"detail":null},{"name":"decreasing","entryType":"measure","startTime":52935.58190000057,"duration":2.6632999777793884,"detail":null},{"name":"decreasing","entryType":"measure","startTime":53206.71489995718,"duration":5.158900022506714,"detail":null},{"name":"decreasing","entryType":"measure","startTime":53222.60989999771,"duration":2.1728999614715576,"detail":null},{"name":"decreasing","entryType":"measure","startTime":53293.36860001087,"duration":5.382599949836731,"detail":null},{"name":"decreasing","entryType":"measure","startTime":53300.98420000076,"duration":2.146399974822998,"detail":null},{"name":"decreasing","entryType":"measure","startTime":53300.98420000076,"duration":46.34589999914169,"detail":null},{"name":"decreasing","entryType":"measure","startTime":53493.25009995699,"duration":1.834000051021576,"detail":null},{"name":"decreasing","entryType":"measure","startTime":53493.25009995699,"duration":2.2687000036239624,"detail":null},{"name":"decreasing","entryType":"measure","startTime":53706.31400001049,"duration":1.376699984073639,"detail":null},{"name":"decreasing","entryType":"measure","startTime":53706.31400001049,"duration":1.9679999947547913,"detail":null},{"name":"decreasing","entryType":"measure","startTime":53857.84229999781,"duration":3.2325000166893005,"detail":null},{"name":"decreasing","entryType":"measure","startTime":54229.11289995909,"duration":6.0085999965667725,"detail":null},{"name":"decreasing","entryType":"measure","startTime":54229.11289995909,"duration":6.567700028419495,"detail":null},{"name":"decreasing","entryType":"measure","startTime":54316.611199975014,"duration":15.729600012302399,"detail":null},{"name":"decreasing","entryType":"measure","startTime":54374.373399972916,"duration":1.3702999949455261,"detail":null},{"name":"decreasing","entryType":"measure","startTime":54650.99659997225,"duration":4.042800009250641,"detail":null},{"name":"decreasing","entryType":"measure","startTime":54661.94609999657,"duration":1.2206000089645386,"detail":null},{"name":"decreasing","entryType":"measure","startTime":54686.27889996767,"duration":2.240400016307831,"detail":null},{"name":"decreasing","entryType":"measure","startTime":54984.92009997368,"duration":4.2391000390052795,"detail":null},{"name":"decreasing","entryType":"measure","startTime":55021.86629998684,"duration":2.298799991607666,"detail":null},{"name":"decreasing","entryType":"measure","startTime":55080.76019996405,"duration":1.990500032901764,"detail":null},{"name":"decreasing","entryType":"measure","startTime":55398.86079996824,"duration":1.3856000304222107,"detail":null},{"name":"decreasing","entryType":"measure","startTime":55495.5121999979,"duration":2.3711000084877014,"detail":null},{"name":"decreasing","entryType":"measure","startTime":55526.37419998646,"duration":1.8435999751091003,"detail":null},{"name":"decreasing","entryType":"measure","startTime":55548.338400006294,"duration":2.9370999932289124,"detail":null},{"name":"decreasing","entryType":"measure","startTime":55579.66089999676,"duration":3.1473000049591064,"detail":null},{"name":"decreasing","entryType":"measure","startTime":55839.12430000305,"duration":1.3876999616622925,"detail":null},{"name":"decreasing","entryType":"measure","startTime":55973.711299955845,"duration":3.1288000345230103,"detail":null},{"name":"decreasing","entryType":"measure","startTime":56468.191100001335,"duration":2.5037999749183655,"detail":null},{"name":"decreasing","entryType":"measure","startTime":56759.58950001001,"duration":4.9686999917030334,"detail":null},{"name":"decreasing","entryType":"measure","startTime":56776.46249997616,"duration":1.311299979686737,"detail":null},{"name":"decreasing","entryType":"measure","startTime":56831.29679995775,"duration":1.8734000325202942,"detail":null},{"name":"decreasing","entryType":"measure","startTime":57246.2281999588,"duration":2.778700053691864,"detail":null},{"name":"decreasing","entryType":"measure","startTime":57296.62479996681,"duration":4.535600006580353,"detail":null},{"name":"decreasing","entryType":"measure","startTime":57331.51120001078,"duration":2.745199978351593,"detail":null},{"name":"decreasing","entryType":"measure","startTime":57395.96939998865,"duration":1.324899971485138,"detail":null},{"name":"decreasing","entryType":"measure","startTime":57640.3205999732,"duration":3.063199996948242,"detail":null},{"name":"decreasing","entryType":"measure","startTime":57686.72469997406,"duration":3.3148000240325928,"detail":null},{"name":"decreasing","entryType":"measure","startTime":57717.87949997187,"duration":1.3421000242233276,"detail":null},{"name":"decreasing","entryType":"measure","startTime":57744.094999969006,"duration":1.8824000358581543,"detail":null},{"name":"decreasing","entryType":"measure","startTime":58787.39969998598,"duration":6.358699977397919,"detail":null},{"name":"decreasing","entryType":"measure","startTime":59528.13679999113,"duration":3.2691999673843384,"detail":null},{"name":"decreasing","entryType":"measure","startTime":60243.41399997473,"duration":2.782100021839142,"detail":null},{"name":"decreasing","entryType":"measure","startTime":61986.20260000229,"duration":4.829099953174591,"detail":null}]}